odoo/addons/mgmtsystem_nonconformity_quality_control_oca/README.rst
odoo/addons/mgmtsystem_nonconformity_quality_control_oca/__init__.py
odoo/addons/mgmtsystem_nonconformity_quality_control_oca/__manifest__.py
odoo/addons/mgmtsystem_nonconformity_quality_control_oca/i18n/it.po
odoo/addons/mgmtsystem_nonconformity_quality_control_oca/i18n/mgmtsystem_nonconformity_quality_control_oca.pot
odoo/addons/mgmtsystem_nonconformity_quality_control_oca/models/__init__.py
odoo/addons/mgmtsystem_nonconformity_quality_control_oca/models/mgmtsystem_nonconformity.py
odoo/addons/mgmtsystem_nonconformity_quality_control_oca/models/qc_inspection.py
odoo/addons/mgmtsystem_nonconformity_quality_control_oca/readme/CONTRIBUTORS.rst
odoo/addons/mgmtsystem_nonconformity_quality_control_oca/readme/DESCRIPTION.rst
odoo/addons/mgmtsystem_nonconformity_quality_control_oca/readme/USAGE.rst
odoo/addons/mgmtsystem_nonconformity_quality_control_oca/static/description/icon.png
odoo/addons/mgmtsystem_nonconformity_quality_control_oca/static/description/index.html
odoo/addons/mgmtsystem_nonconformity_quality_control_oca/views/mgmtsystem_nonconformity.xml
odoo/addons/mgmtsystem_nonconformity_quality_control_oca/views/qc_inspection.xml
odoo14_addon_mgmtsystem_nonconformity_quality_control_oca-14.0.1.0.1.dist-info/METADATA
odoo14_addon_mgmtsystem_nonconformity_quality_control_oca-14.0.1.0.1.dist-info/WHEEL
odoo14_addon_mgmtsystem_nonconformity_quality_control_oca-14.0.1.0.1.dist-info/top_level.txt
odoo14_addon_mgmtsystem_nonconformity_quality_control_oca-14.0.1.0.1.dist-info/RECORD
